[
    {
        "id": 1,
        "title": "如何创建课节1",
        "creattime": "2020/09/27 12:30",
        "content": "<p>满足多种教学形态，不管是1对1教学、课外兴趣小班课还是大型直播公开课，帮你轻松搭建属于自己的在线课堂满足多种教学形态，不管是1对1教学、课外兴趣小班课还是大型直播公开课，帮你轻松搭建属于自己的在线课堂满足多种教学形态，不管是1对1教学、课外兴趣小班课还是大型直播公开课，帮你轻松搭建属于自己的在线课堂满足多种教学形态，不管是1对1教学、课外兴趣小班课还是大型直播公开课，帮你轻松</p><img src=''/><p>满足多种教学形态，不管是1对1教学、课外兴趣小班课还是大型直播公开课，帮你轻松搭建属于自己的在线课堂满足多种教学形态，不管是1对1教学、课外兴趣小班课还是大型直播公开课，帮你轻松搭建属于自己的在线课堂满足多种教学形态，不管是1对1教学、课外兴趣小班课还是大型直播公开课，帮你轻松搭建属于自己的在线课堂满足多种教学形态，不管是1对1教学、课外兴趣小班课还是大型直播公开课，帮你轻松</p><img src=''/><p>满足多种教学形态，不管是1对1教学、课外兴趣小班课还是大型直播公开课，帮你轻松搭建属于自己的在线课堂满足多种教学形态，不管是1对1教学、课外兴趣小班课还是大型直播公开课，帮你轻松搭建属于自己的在线课堂满足多种教学形态，不管是1对1教学、课外兴趣小班课还是大型直播公开课，帮你轻松搭建属于自己的在线课堂满足多种教学形态，不管是1对1教学、课外兴趣小班课还是大型直播公开课，帮你轻松</p><img src=''/>"
    },{
        "id": 2,
        "title": "如何创建课节2",
        "creattime": "2020/10/22 12:30",
        "content": "<p>满足多种教学形态，不管是1对1教学、课外兴趣小班课还是大型直播公开课，帮你轻松搭建属于自己的在线课堂满足多种教学形态，不管是1对1教学、课外兴趣小班课还是大型直播公开课，帮你轻松搭建属于自己的在线课堂满足多种教学形态，不管是1对1教学、课外兴趣小班课还是大型直播公开课，帮你轻松搭建属于自己的在线课堂满足多种教学形态，不管是1对1教学、课外兴趣小班课还是大型直播公开课，帮你轻松</p><img src=''/><p>满足多种教学形态，不管是1对1教学、课外兴趣小班课还是大型直播公开课，帮你轻松搭建属于自己的在线课堂满足多种教学形态，不管是1对1教学、课外兴趣小班课还是大型直播公开课，帮你轻松搭建属于自己的在线课堂满足多种教学形态，不管是1对1教学、课外兴趣小班课还是大型直播公开课，帮你轻松搭建属于自己的在线课堂满足多种教学形态，不管是1对1教学、课外兴趣小班课还是大型直播公开课，帮你轻松</p><img src=''/><p>满足多种教学形态，不管是1对1教学、课外兴趣小班课还是大型直播公开课，帮你轻松搭建属于自己的在线课堂满足多种教学形态，不管是1对1教学、课外兴趣小班课还是大型直播公开课，帮你轻松搭建属于自己的在线课堂满足多种教学形态，不管是1对1教学、课外兴趣小班课还是大型直播公开课，帮你轻松搭建属于自己的在线课堂满足多种教学形态，不管是1对1教学、课外兴趣小班课还是大型直播公开课，帮你轻松</p><img src=''/>"
    }
]